{
    "@odata.type": "#microsoft.graph.commsNotifications",
    "value": [
        {
            "@odata.type": "#microsoft.graph.commsNotification",
            "changeType": "updated",
            "resource": "/app/calls/631f6000-766a-4c6f-9da3-8755ebe44d19",
            "resourceUrl": "/communications/calls/631f6000-766a-4c6f-9da3-8755ebe44d19",
            "resourceData": {
                "@odata.type": "#microsoft.graph.call",
                "state": "establishing",
                "callChainId": "43fd2643-9526-4154-b335-083d06ad25f3"
            }
        }
    ]
}